s1etad/__init__.py
s1etad/__main__.py
s1etad/_jupyter_support.py
s1etad/_s1utils.py
s1etad/geometry.py
s1etad/kmz.py
s1etad/product.py
s1etad/ql.py
s1etad/utils.py
s1etad/cli/__init__.py
s1etad/cli/exportkmz.py
s1etad/cli/main.py
s1etad/cli/ql.py
s1etad/cli/utils.py
s1etad-0.6.1.dist-info/licenses/AUTHORS.rst
s1etad-0.6.1.dist-info/licenses/LICENSE.txt
s1etad-0.6.1.dist-info/METADATA
s1etad-0.6.1.dist-info/WHEEL
s1etad-0.6.1.dist-info/entry_points.txt
s1etad-0.6.1.dist-info/top_level.txt
s1etad-0.6.1.dist-info/RECORD
