Metadata-Version: 2.4
Name: s1etad
Version: 0.6.1
Summary: Reader for Sentinel-1 Extended Timing Annotation Dataset
Author: Nuno Miranda, Antonio Valentino
Author-email: s1etad@esa.int
License: MIT License
Project-URL: Homepage, https://github.com/s1tools/s1-etad
Project-URL: Documentation, https://s1etad.readthedocs.io
Project-URL: Repository, https://github.com/s1tools/s1-etad
Project-URL: Changelog, https://github.com/s1tools/s1-etad/blob/main/CHANGELOG.rst
Project-URL: Issues, https://github.com/s1tools/s1-etad/issues
Keywords: sentinel,copernicus,esa,remote-sensing,satellite-imagery
Classifier: Development Status :: 4 - Beta
Classifier: Intended Audience :: Science/Research
Classifier: Operating System :: OS Independent
Classifier: Programming Language :: Python :: 3
Classifier: Programming Language :: Python :: 3 :: Only
Classifier: Topic :: Scientific/Engineering
Requires-Python: >=3.10
License-File: LICENSE.txt
License-File: AUTHORS.rst
Requires-Dist: numpy
Requires-Dist: scipy
Requires-Dist: lxml
Requires-Dist: netCDF4
Requires-Dist: pandas
Requires-Dist: shapely>=1.8
Requires-Dist: pymap3d
Provides-Extra: kmz
Requires-Dist: simplekml; extra == "kmz"
Requires-Dist: gdal; extra == "kmz"
Requires-Dist: matplotlib; extra == "kmz"
Provides-Extra: ql
Requires-Dist: gdal; extra == "ql"
Requires-Dist: matplotlib; extra == "ql"
Provides-Extra: cli
Requires-Dist: argcomplete; extra == "cli"
Provides-Extra: all
Requires-Dist: s1etad[kmz]; extra == "all"
Requires-Dist: s1etad[ql]; extra == "all"
Requires-Dist: s1etad[cli]; extra == "all"
Dynamic: license-file
